{"sections":{"952aa2e8-ad78-443b-8e6d-38922975f6e3":{"type":"rich-text","blocks":{"template--17231003779292__952aa2e8-ad78-443b-8e6d-38922975f6e3-heading-1":{"type":"heading","settings":{"title":"Contact Us","use_h1":true}}},"block_order":["template--17231003779292__952aa2e8-ad78-443b-8e6d-38922975f6e3-heading-1"],"settings":{"height":"medium","text_alignment":"center","full_width":false,"color_scheme":"default"}},"a6fd1bfc-311c-4bd4-9cef-5846834b8417":{"type":"map","settings":{"full_width":true,"color_scheme":"1","heading":"Cedarcide","address":"<p>Phone: <a href=\"tel:8008421464\" title=\"Call 8008421464\">800-842-1464<\/a><br\/>Email: <a href=\"mailto:questions@cedarcide.com\" title=\"Send an email to questions@cedarcide.com\">questions@cedarcide.com<\/a><\/p><p>Mon-Fri: 8a-6p (CST)<br\/>Sat-Sun: CLOSED<\/p><p>1025 N. MILL STREET<br\/>SUITE D, LEWISVILLE, <br\/>TEXAS, 75057<\/p>","button":"Directions","show_pin":true,"show_feature_image":false,"map_address":"1025 N MILL STREET STE D LEWISVILLE TEXAS 75057","api_key":"AIzaSyAnSHKjqKZJ34MWkYw5efC4iUma3ctrPRo","map_type":"dynamic","map_style":"default"}},"main":{"type":"main-contact","blocks":{"name":{"type":"name_input","settings":{"half_width":true}},"email":{"type":"email_input","settings":{"half_width":true}},"message":{"type":"message_input","settings":{"half_width":false}}},"block_order":["name","email","message"],"settings":{"show_page_title":false,"use_columns":true,"contact_title":"Customer Service","contact_text":"<p>Send us an email or click the chat icon to get assistance.<\/p>"}},"custom_liquid_9pLBCw":{"type":"custom-liquid","custom_css":[".fully-spaced-row--medium {margin-top: 0; margin-bottom: 0;}"],"settings":{"full_width":true,"code":"<script>\nvar _learnq = _learnq || []; \nvar page = window.location.pathname;\n_learnq.push(['track', 'Viewed Page',\n{url: page}\n]);\n<\/script>"}}},"order":["952aa2e8-ad78-443b-8e6d-38922975f6e3","a6fd1bfc-311c-4bd4-9cef-5846834b8417","main","custom_liquid_9pLBCw"]}